moa_exoplanet_archive/__init__.py
moa_exoplanet_archive/column_name.py
moa_exoplanet_archive/count_file_versions.py
moa_exoplanet_archive/file_check.py
moa_exoplanet_archive/file_count.py
moa_exoplanet_archive/merge_files.py
moa_exoplanet_archive/merge_transfer_cli.py
moa_exoplanet_archive-0.1.3.dist-info/WHEEL
moa_exoplanet_archive-0.1.3.dist-info/entry_points.txt
moa_exoplanet_archive-0.1.3.dist-info/METADATA
moa_exoplanet_archive-0.1.3.dist-info/RECORD
