Metadata-Version: 2.1
Name: moa-exoplanet-archive
Version: 0.1.3
Summary: 
Author: Greg Olmschenk
Author-email: greg@olmschenk.com
Requires-Python: >=3.9,<4.0
Classifier: Programming Language :: Python :: 3
Classifier: Programming Language :: Python :: 3.9
Classifier: Programming Language :: Python :: 3.10
Classifier: Programming Language :: Python :: 3.11
Requires-Dist: astropy (>=5.2.1,<6.0.0)
Requires-Dist: backports-strenum (>=1.1.1,<2.0.0)
Requires-Dist: numpy (>=1.24.1,<2.0.0)
Requires-Dist: pandas (>=1.5.3,<2.0.0)
Requires-Dist: pysftp (>=0.2.9,<0.3.0)
Requires-Dist: tabulate (>=0.9.0,<0.10.0)
